IP_pack/__init__.py
IP_pack/module1.py
IP_pack/module2.py
IP_pack-0.1.dist-info/LICENCE
IP_pack-0.1.dist-info/METADATA
IP_pack-0.1.dist-info/WHEEL
IP_pack-0.1.dist-info/top_level.txt
IP_pack-0.1.dist-info/RECORD
